jupyterfair/__init__.py
jupyterfair/_version.py
jupyterfair/config.py
jupyterfair/handlers.py
jupyterfair/labextension/package.json
jupyterfair/labextension/schemas/jupyterfair/package.json.orig
jupyterfair/labextension/schemas/jupyterfair/plugin.json
jupyterfair/labextension/static/382.624cf384ea54a54ec161.js
jupyterfair/labextension/static/747.d3bbc79973c8ae7854ce.js
jupyterfair/labextension/static/remoteEntry.b6c4f90301b00f4e7f5c.js
jupyterfair/labextension/static/style.js
jupyterfair/labextension/static/third-party-licenses.json
jupyterfair/tests/__init__.py
jupyterfair/tests/test_fourtu.py
jupyterfair-0.2.0b1.data/data/etc/jupyter/jupyter_notebook_config.d/jupyterfair.json
jupyterfair-0.2.0b1.data/data/etc/jupyter/jupyter_server_config.d/jupyterfair.json
jupyterfair-0.2.0b1.data/data/share/jupyter/labextensions/jupyterfair/install.json
jupyterfair-0.2.0b1.data/data/share/jupyter/labextensions/jupyterfair/package.json
jupyterfair-0.2.0b1.data/data/share/jupyter/labextensions/jupyterfair/schemas/jupyterfair/package.json.orig
jupyterfair-0.2.0b1.data/data/share/jupyter/labextensions/jupyterfair/schemas/jupyterfair/plugin.json
jupyterfair-0.2.0b1.data/data/share/jupyter/labextensions/jupyterfair/static/382.624cf384ea54a54ec161.js
jupyterfair-0.2.0b1.data/data/share/jupyter/labextensions/jupyterfair/static/747.d3bbc79973c8ae7854ce.js
jupyterfair-0.2.0b1.data/data/share/jupyter/labextensions/jupyterfair/static/remoteEntry.b6c4f90301b00f4e7f5c.js
jupyterfair-0.2.0b1.data/data/share/jupyter/labextensions/jupyterfair/static/style.js
jupyterfair-0.2.0b1.data/data/share/jupyter/labextensions/jupyterfair/static/third-party-licenses.json
jupyterfair-0.2.0b1.dist-info/LICENSE
jupyterfair-0.2.0b1.dist-info/METADATA
jupyterfair-0.2.0b1.dist-info/WHEEL
jupyterfair-0.2.0b1.dist-info/top_level.txt
jupyterfair-0.2.0b1.dist-info/RECORD
