Metadata-Version: 2.1
Name: jupyterfair
Version: 0.2.0b1
Summary: a tool for seamless integration of Jupyter-based research environments and research data repositories based on the fairly package.
Home-page: https://github.com/ITC-CRIB/JupyterFAIR
Author: JupyterFAIR Team
Author-email: m.g.garciaalvarez@tudelft.nl
License: MIT License
Keywords: Jupyter,JupyterLab,JupyterLab3
Platform: Linux
Platform: Mac OS X
Platform: Windows
Classifier: License :: OSI Approved :: BSD License
Classifier: Programming Language :: Python
Classifier: Programming Language :: Python :: 3
Classifier: Programming Language :: Python :: 3.7
Classifier: Programming Language :: Python :: 3.8
Classifier: Programming Language :: Python :: 3.9
Classifier: Programming Language :: Python :: 3.10
Classifier: Framework :: Jupyter
Classifier: Framework :: Jupyter :: JupyterLab
Classifier: Framework :: Jupyter :: JupyterLab :: 3
Classifier: Framework :: Jupyter :: JupyterLab :: Extensions
Classifier: Framework :: Jupyter :: JupyterLab :: Extensions :: Prebuilt
Requires-Python: >=3.7
License-File: LICENSE
Requires-Dist: jupyter-server (<2,>=1.6)
Requires-Dist: requests (>=2.27.1)
Requires-Dist: python-dotenv (==0.20.0)
Requires-Dist: pytest (==7.1.2)
Requires-Dist: jupyter-packaging (==0.12.0)
Requires-Dist: nodejs (==0.1.1)
Requires-Dist: fairly (==0.2.1)
